<?xml version="1.0" encoding="UTF-8" standalone="yes"?><annotation><filename>image49485.jpg</filename><object><bndbox><xmax>3067.2375</xmax><xmin>1883.6693</xmin><ymax>2836.9343</ymax><ymin>451.07367</ymin></bndbox><cadmodelname></cadmodelname><id>1</id><name>Typlabel-China</name><partId></partId><segmentation><point><index>0</index><x>1961.0054</x><y>2836.9343</y></point><point><index>1</index><x>2491.7998</x><y>2831.511</y></point><point><index>2</index><x>2748.4583</x><y>2824.554</y></point><point><index>3</index><x>2988.2754</x><y>2816.6045</y></point><point><index>4</index><x>3000.16</x><y>2814.2275</y></point><point><index>5</index><x>3009.6675</x><y>2811.5535</y></point><point><index>6</index><x>3021.552</x><y>2806.7998</y></point><point><index>7</index><x>3032.2478</x><y>2799.9663</y></point><point><index>8</index><x>3044.7266</x><y>2789.5674</y></point><point><index>9</index><x>3051.56</x><y>2780.357</y></point><point><index>10</index><x>3059.5823</x><y>2766.3926</y></point><point><index>11</index><x>3064.336</x><y>2754.508</y></point><point><index>12</index><x>3067.01</x><y>2745.2976</y></point><point><index>13</index><x>3067.2375</x><y>2729.2927</y></point><point><index>14</index><x>3063.9465</x><y>2669.1338</y></point><point><index>15</index><x>2990.3896</x><y>1453.4259</y></point><point><index>16</index><x>2967.3394</x><y>1091.464</y></point><point><index>17</index><x>2923.9878</x><y>497.12296</y></point><point><index>18</index><x>2922.205</x><y>486.72406</y></point><point><index>19</index><x>2912.6975</x><y>473.05692</y></point><point><index>20</index><x>2908.2407</x><y>467.11472</y></point><point><index>21</index><x>2901.4072</x><y>462.65802</y></point><point><index>22</index><x>2896.0305</x><y>458.79858</y></point><point><index>23</index><x>2887.7114</x><y>455.82745</y></point><point><index>24</index><x>2878.2039</x><y>453.45056</y></point><point><index>25</index><x>2868.102</x><y>451.07367</y></point><point><index>26</index><x>2854.4348</x><y>451.3708</y></point><point><index>27</index><x>2815.216</x><y>458.79858</y></point><point><index>28</index><x>2784.0195</x><y>462.95813</y></point><point><index>29</index><x>2623.73</x><y>486.85114</y></point><point><index>30</index><x>2428.9797</x><y>511.35443</y></point><point><index>31</index><x>2248.4478</x><y>527.7906</y></point><point><index>32</index><x>2014.6799</x><y>545.3232</y></point><point><index>33</index><x>1987.6514</x><y>548.72614</y></point><point><index>34</index><x>1974.5785</x><y>557.0452</y></point><point><index>35</index><x>1961.8027</x><y>565.6615</y></point><point><index>36</index><x>1955.5634</x><y>574.2777</y></point><point><index>37</index><x>1945.4615</x><y>586.1622</y></point><point><index>38</index><x>1941.302</x><y>598.64087</y></point><point><index>39</index><x>1940.7078</x><y>632.2144</y></point><point><index>40</index><x>1929.4554</x><y>1062.6044</y></point><point><index>41</index><x>1914.8696</x><y>1597.0682</y></point><point><index>42</index><x>1900.8057</x><y>2230.2458</y></point><point><index>43</index><x>1891.7231</x><y>2593.5525</y></point><point><index>44</index><x>1883.6693</x><y>2754.6003</y></point><point><index>45</index><x>1884.4313</x><y>2773.5894</y></point><point><index>46</index><x>1887.1053</x><y>2783.394</y></point><point><index>47</index><x>1891.562</x><y>2793.4958</y></point><point><index>48</index><x>1895.7216</x><y>2801.5178</y></point><point><index>49</index><x>1911.409</x><y>2818.8472</y></point><point><index>50</index><x>1921.2137</x><y>2825.6807</y></point><point><index>51</index><x>1933.0981</x><y>2830.7317</y></point><point><index>52</index><x>1945.5768</x><y>2835.4854</y></point></segmentation></object><segmented>1</segmented><size><depth>3</depth><height>3456</height><width>4608</width></size><source><database>labelingtool/57-ISI-carsign-label</database></source></annotation>