<?xml version='1.0' encoding='UTF-8'?>
<annotation>
  <segmented>1</segmented>
  <object>
    <bndbox>
      <xmin>0</xmin>
      <ymin>664</ymin>
      <xmax>1729</xmax>
      <ymax>1291</ymax>
    </bndbox>
    <id>1</id>
    <name>RDS-NAR</name>
    <partId/>
    <segmentation>
      <point>
        <index>0</index>
        <x>24</x>
        <y>693</y>
      </point>
      <point>
        <index>1</index>
        <x>0</x>
        <y>1291</y>
      </point>
      <point>
        <index>2</index>
        <x>1704</x>
        <y>1261</y>
      </point>
      <point>
        <index>3</index>
        <x>1729</x>
        <y>664</y>
      </point>
    </segmentation>
  </object>
  <size>
    <depth>3</depth>
    <width>1728</width>
    <height>2304</height>
  </size>
  <filename>image_825.xml</filename>
</annotation>
