<?xml version='1.0' encoding='UTF-8'?>
<annotation>
  <segmented>1</segmented>
  <object>
    <bndbox>
      <xmin>6</xmin>
      <ymin>502</ymin>
      <xmax>1216</xmax>
      <ymax>990</ymax>
    </bndbox>
    <id>1</id>
    <name>RDS-NAR</name>
    <partId/>
    <segmentation>
      <point>
        <index>0</index>
        <x>206</x>
        <y>502</y>
      </point>
      <point>
        <index>1</index>
        <x>6</x>
        <y>853</y>
      </point>
      <point>
        <index>2</index>
        <x>1015</x>
        <y>990</y>
      </point>
      <point>
        <index>3</index>
        <x>1216</x>
        <y>638</y>
      </point>
    </segmentation>
  </object>
  <size>
    <depth>3</depth>
    <width>1728</width>
    <height>2304</height>
  </size>
  <filename>image_859.xml</filename>
</annotation>
