<?xml version='1.0' encoding='UTF-8'?>
<annotation>
  <segmented>1</segmented>
  <object>
    <bndbox>
      <xmin>26</xmin>
      <ymin>306</ymin>
      <xmax>1160</xmax>
      <ymax>666</ymax>
    </bndbox>
    <id>1</id>
    <name>RDS-NAR</name>
    <partId/>
    <segmentation>
      <point>
        <index>0</index>
        <x>26</x>
        <y>306</y>
      </point>
      <point>
        <index>1</index>
        <x>51</x>
        <y>638</y>
      </point>
      <point>
        <index>2</index>
        <x>1160</x>
        <y>666</y>
      </point>
      <point>
        <index>3</index>
        <x>1134</x>
        <y>334</y>
      </point>
    </segmentation>
  </object>
  <size>
    <depth>3</depth>
    <width>1728</width>
    <height>2304</height>
  </size>
  <filename>image_754.xml</filename>
</annotation>
